fw_gear_nifti_to_mips/__init__.py
fw_gear_nifti_to_mips/converter.py
fw_gear_nifti_to_mips/parser.py
fw_gear_nifti_to_mips-0.1.1.dist-info/METADATA
fw_gear_nifti_to_mips-0.1.1.dist-info/WHEEL
fw_gear_nifti_to_mips-0.1.1.dist-info/RECORD
