Metadata-Version: 2.4
Name: fw-gear-nifti-to-mips
Version: 0.1.1
Summary: Convert nifti to MIPS.
Author-email: Flywheel <support@flywheel.io>
License-Expression: MIT
Requires-Python: <4.0,>=3.12
Requires-Dist: flywheel-gear-toolkit<0.7,>=0.6
Requires-Dist: flywheel-sdk<19,>=18
Requires-Dist: idna>=3.0
Requires-Dist: nibabel>=5.1.0
Requires-Dist: numpy<2,>=1.26
Requires-Dist: pillow<11,>=10
